real_time_analog_monitoring_tool-0.0.9.dist-info/DESCRIPTION.rst
real_time_analog_monitoring_tool-0.0.9.dist-info/METADATA
real_time_analog_monitoring_tool-0.0.9.dist-info/RECORD
real_time_analog_monitoring_tool-0.0.9.dist-info/WHEEL
real_time_analog_monitoring_tool-0.0.9.dist-info/metadata.json
real_time_analog_monitoring_tool-0.0.9.dist-info/top_level.txt
rtamt/__init__.py
rtamt/enumerations/__init__.py
rtamt/enumerations/bool_ops.py
rtamt/exception/__init__.py
rtamt/exception/stl/__init__.py
rtamt/exception/stl/exception.py
rtamt/interval/__init__.py
rtamt/interval/interval.py
rtamt/lib/__init__.py
rtamt/lib/rtamt_stl_library_wrapper/__init__.py
rtamt/node/__init__.py
rtamt/node/abstract_node.py
rtamt/node/arithmetic/__init__.py
rtamt/node/stl/__init__.py
rtamt/node/stl/abs.py
rtamt/node/stl/addition.py
rtamt/node/stl/always.py
rtamt/node/stl/conjunction.py
rtamt/node/stl/disjunction.py
rtamt/node/stl/division.py
rtamt/node/stl/eventually.py
rtamt/node/stl/fall.py
rtamt/node/stl/historically.py
rtamt/node/stl/iff.py
rtamt/node/stl/implies.py
rtamt/node/stl/multiplication.py
rtamt/node/stl/neg.py
rtamt/node/stl/node.py
rtamt/node/stl/once.py
rtamt/node/stl/precedes.py
rtamt/node/stl/predicate.py
rtamt/node/stl/rise.py
rtamt/node/stl/since.py
rtamt/node/stl/subtraction.py
rtamt/node/stl/temporal_node.py
rtamt/node/stl/until.py
rtamt/node/stl/variable.py
rtamt/node/stl/xor.py
rtamt/operation/__init__.py
rtamt/operation/abstract_operation.py
rtamt/operation/sample.py
rtamt/operation/arithmetic/__init__.py
rtamt/operation/arithmetic/abs_operation.py
rtamt/operation/arithmetic/addition_operation.py
rtamt/operation/arithmetic/division_operation.py
rtamt/operation/arithmetic/multiplication_operation.py
rtamt/operation/arithmetic/subtraction_operation.py
rtamt/operation/arithmetic_ct/__init__.py
rtamt/operation/arithmetic_ct/abs_operation.py
rtamt/operation/arithmetic_ct/addition_operation.py
rtamt/operation/arithmetic_ct/division_operation.py
rtamt/operation/arithmetic_ct/multiplication_operation.py
rtamt/operation/arithmetic_ct/subtraction_operation.py
rtamt/operation/stl/__init__.py
rtamt/operation/stl/always_operation.py
rtamt/operation/stl/and_operation.py
rtamt/operation/stl/eventually_operation.py
rtamt/operation/stl/fall_operation.py
