Metadata-Version: 2.0
Name: real-time-analog-monitoring-tool
Version: 0.0.9
Summary: A tool for real time analog monitoring.
Home-page: https://github.com/nickovic/rtamt
Author: Nickovic Dejan, Tomoya Yamaguchi
Author-email: dejan.nickovic@ait.ac.at, tomoya.yamaguchi@toyota.com
License: BSD
Platform: UNKNOWN
Classifier: License :: OSI Approved :: BSD License
Classifier: Programming Language :: Python :: 2.7
Classifier: Programming Language :: C++
Requires-Dist: antlr4-python2-runtime (==4.5)
Requires-Dist: enum34
